soltxs/__init__.py
soltxs/normalizer/__init__.py
soltxs/normalizer/models.py
soltxs/normalizer/normalizers/__init__.py
soltxs/normalizer/normalizers/geyser.py
soltxs/normalizer/normalizers/rpc.py
soltxs/normalizer/normalizers/shared.py
soltxs/parser/__init__.py
soltxs/parser/models.py
soltxs/parser/addons/__init__.py
soltxs/parser/addons/compute_units.py
soltxs/parser/addons/instruction_count.py
soltxs/parser/addons/loaded_addresses.py
soltxs/parser/addons/platform_identifier.py
soltxs/parser/addons/token_transfer.py
soltxs/parser/addons/transaction_status.py
soltxs/parser/parsers/__init__.py
soltxs/parser/parsers/computeBudget.py
soltxs/parser/parsers/pumpfun.py
soltxs/parser/parsers/raydiumAMM.py
soltxs/parser/parsers/systemProgram.py
soltxs/parser/parsers/tokenProgram.py
soltxs/parser/parsers/unknown.py
soltxs/resolver/__init__.py
soltxs/resolver/models.py
soltxs/resolver/resolvers/__init__.py
soltxs/resolver/resolvers/pumpfun.py
soltxs/resolver/resolvers/raydium.py
soltxs/resolver/resolvers/unknown.py
tests/__init__.py
tests/conftest.py
tests/test_addon.py
tests/test_normalize.py
tests/test_resolve.py
tests/programs/__init__.py
tests/programs/test_pumpfun.py
tests/programs/test_raydium.py
soltxs-1.0.8.dist-info/METADATA
soltxs-1.0.8.dist-info/WHEEL
soltxs-1.0.8.dist-info/top_level.txt
soltxs-1.0.8.dist-info/RECORD
